Flask_YoloAPI-0.1.5.dist-info/METADATA
Flask_YoloAPI-0.1.5.dist-info/RECORD
Flask_YoloAPI-0.1.5.dist-info/WHEEL
Flask_YoloAPI-0.1.5.dist-info/top_level.txt
flask_yoloapi/__init__.py
flask_yoloapi/endpoint.py
flask_yoloapi/exceptions.py
flask_yoloapi/types.py
flask_yoloapi/utils.py
tests/__init__.py
tests/conftest.py
tests/mock_app.py
tests/test_app.py
