Metadata-Version: 2.1
Name: Flask-YoloAPI
Version: 0.1.5
Summary: Simply the best Flask API library
Home-page: https://github.com/skftn/flask-yoloapi
Author: Sander Ferdinand
Author-email: sa.ferdinand@gmail.com
License: UNKNOWN
Download-URL: https://github.com/skftn/flask-yoloapi/archive/master.zip
Keywords: flask api flapi yoloapi
Platform: UNKNOWN
Classifier: Development Status :: 4 - Beta
Classifier: Environment :: Web Environment
Classifier: Intended Audience :: Developers
Classifier: License :: OSI Approved :: MIT License
Classifier: Operating System :: OS Independent
Classifier: Topic :: Software Development :: Libraries :: Python Modules
Classifier: Topic :: Utilities
Classifier: Programming Language :: Python
Requires-Dist: flask
Requires-Dist: python-dateutil
